__init__.py
auto_submit_tips.py
config/creds-secret.yaml
kicktipp-0.2.1.dist-info/METADATA
kicktipp-0.2.1.dist-info/WHEEL
kicktipp-0.2.1.dist-info/top_level.txt
kicktipp-0.2.1.dist-info/RECORD
