Metadata-Version: 2.1
Name: kicktipp
Version: 0.2.1
